Update_gempa/__init__.py
newearthquake_BMKG-0.2.dist-info/LICENSE
newearthquake_BMKG-0.2.dist-info/METADATA
newearthquake_BMKG-0.2.dist-info/WHEEL
newearthquake_BMKG-0.2.dist-info/top_level.txt
newearthquake_BMKG-0.2.dist-info/RECORD
