Metadata-Version: 2.1
Name: newearthquake-BMKG
Version: 0.2
Summary: This package get the last update earthquake from BMKG Indonesia
Home-page: https://github.com/paten26/BMKG_latest_earthquake
Author: Lukas Yulianto
Author-email: paten26@gmail.com
Classifier: Programming Language :: Python :: 3
Classifier: License :: OSI Approved :: GNU General Public License v3 (GPLv3)
Classifier: Operating System :: OS Independent
Requires-Python: >=3.6
License-File: LICENSE
